aistudio_cognition/cognibot/models.py
aistudio_cognition/km/genai/genai.py
aistudio_cognition/km/genai/models/genai_settings.py
aistudio_cognition/km/qnamaker/models/qnamaker_settings.py
aistudio_cognition/km/qnamaker/qnamaker.py
aistudio_cognition/models/__init__.py
aistudio_cognition/models/response_status.py
aistudio_cognition/nlu/luis/__init__.py
aistudio_cognition/nlu/luis/luis.py
aistudio_cognition/nlu/luis/models/__init__.py
aistudio_cognition/nlu/luis/models/luis_settings.py
aistudio_cognition/nlu/luis/prediction.py
aistudio_cognition/nlu/luis/rule.py
aistudio_cognition/nlu/models.py
aistudio_cognition-3.7.0.dist-info/METADATA
aistudio_cognition-3.7.0.dist-info/WHEEL
aistudio_cognition-3.7.0.dist-info/RECORD
